requests_enhanced/__init__.py
requests_enhanced/adapters.py
requests_enhanced/exceptions.py
requests_enhanced/logging.py
requests_enhanced/oauth.py
requests_enhanced/py.typed
requests_enhanced/sessions.py
requests_enhanced/utils.py
requests_enhanced-1.0.1.dist-info/licenses/LICENSE
requests_enhanced-1.0.1.dist-info/METADATA
requests_enhanced-1.0.1.dist-info/WHEEL
requests_enhanced-1.0.1.dist-info/top_level.txt
requests_enhanced-1.0.1.dist-info/RECORD
