Metadata-Version: 2.4
Name: requests-enhanced
Version: 1.0.1
Summary: An enhanced wrapper for the requests library with HTTP/2, HTTP/3, OAuth authentication, retry, timeout, and logging capabilities
Author: Kevin Hollingworth
Author-email: khollingworth@me.com
License: MIT
Project-URL: Bug Tracker, https://github.com/khollingworth/requests-enhanced/issues
Project-URL: Documentation, https://github.com/khollingworth/requests-enhanced/tree/main/docs
Project-URL: Source Code, https://github.com/khollingworth/requests-enhanced
Classifier: License :: OSI Approved :: MIT License
Classifier: Programming Language :: Python :: 3
Classifier: Programming Language :: Python :: 3.8
Classifier: Programming Language :: Python :: 3.9
Classifier: Programming Language :: Python :: 3.10
Classifier: Programming Language :: Python :: 3.11
Classifier: Topic :: Software Development :: Libraries :: Python Modules
Classifier: Intended Audience :: Developers
Classifier: Operating System :: OS Independent
Requires-Python: >=3.8
License-File: LICENSE
Requires-Dist: requests<3.0.0,>=2.25.0
Requires-Dist: urllib3<2.0.0,>=1.25.4
Requires-Dist: certifi>=2017.4.17
Provides-Extra: dev
Requires-Dist: pytest>=7.0.0; extra == "dev"
Requires-Dist: pytest-cov>=3.0.0; extra == "dev"
Requires-Dist: pytest-httpserver>=1.0.0; extra == "dev"
Requires-Dist: black>=22.3.0; extra == "dev"
Requires-Dist: flake8>=4.0.0; extra == "dev"
Requires-Dist: mypy>=1.0.0; extra == "dev"
Requires-Dist: isort>=5.0.0; extra == "dev"
Provides-Extra: http2
Requires-Dist: h2<5.0.0,>=4.0.0; extra == "http2"
Requires-Dist: hyperframe<7.0.0,>=6.0.0; extra == "http2"
Requires-Dist: hpack<5.0.0,>=4.0.0; extra == "http2"
Provides-Extra: http3
Requires-Dist: aioquic<1.0.0,>=0.9.20; extra == "http3"
Requires-Dist: asyncio<4.0.0,>=3.4.3; extra == "http3"
Provides-Extra: oauth
Requires-Dist: requests-oauthlib<2.0.0,>=1.3.0; extra == "oauth"
Requires-Dist: oauthlib<4.0.0,>=3.1.0; extra == "oauth"
Provides-Extra: all
Requires-Dist: h2<5.0.0,>=4.0.0; extra == "all"
Requires-Dist: hyperframe<7.0.0,>=6.0.0; extra == "all"
Requires-Dist: hpack<5.0.0,>=4.0.0; extra == "all"
Requires-Dist: aioquic<1.0.0,>=0.9.20; extra == "all"
Requires-Dist: asyncio<4.0.0,>=3.4.3; extra == "all"
Requires-Dist: requests-oauthlib<2.0.0,>=1.3.0; extra == "all"
Requires-Dist: oauthlib<4.0.0,>=3.1.0; extra == "all"
Dynamic: license-file
